2022.4/CQU_MIPS/lab1_1/seg7.v

`timescale 1ns / 1ps

module seg7(
    input wire [3:0]din,
    output reg [6:0]dout
    );
 
    always@(*)
    case(din)
        5'h0:dout = 7'b000_0001;
        5'h1:dout = 7'b100_1111;
        5'h2:dout = 7'b001_0010; 
        5'h3:dout = 7'b000_0110;
        5'h4:dout = 7'b100_1100;
        5'h5:dout = 7'b010_0100;
        5'h6:dout = 7'b010_0000;
        5'h7:dout = 7'b000_1111;
        5'h8:dout = 7'b000_0000;
        5'h9:dout = 7'b000_0100;
        5'ha:dout = 7'b000_1000;
        5'hb:dout = 7'b110_0000;
        5'hc:dout = 7'b011_0001;
        5'hd:dout = 7'b100_0010;
        5'he:dout = 7'b011_0000;
        5'hf:dout = 7'b011_1000;
        default:dout = 7'b111_1111;        
    endcase
    
    
endmodule

2022.4/CQU_MIPS/lab2/display.v
`timescale 1ns / 1ps
//////////////////////////////////////////////////////////////////////////////////
// Company: 
// Engineer: 
// 
// Create Date: 2015/09/17 01:12:00
// Design Name: 
// Module Name: display
// Project Name: 
// Target Devices: 
// Tool Versions: 
// Description: 
// 
// Dependencies: 
// 
// Revision:
// Revision 0.01 - File Created
// Additional Comments:
// 
//////////////////////////////////////////////////////////////////////////////////

module display(
    input wire clk,reset,
    input wire [31:0]s,
    output wire [6:0]seg,
    output reg [7:0]ans
    );
    reg [20:0]count;
    reg [4:0]digit; 
    always@(posedge clk,posedge reset)
    if(reset)  
        count = 0;
    else 
        count = count + 1;
       
    always @(posedge clk)
    case(count[20:18])
        0:begin
            ans = 8'b11111110;
            digit = s[3:0];
        end
        
        1:begin
            ans = 8'b11111101;
            digit = s[7:4];
        end

        2:begin
            ans = 8'b11111011;
            digit =s[11:8];
        end
        
        3:begin
            ans = 8'b11110111;
            digit = s[15:12];
        end
        
         4:begin
             ans = 8'b11101111;
             digit = s[19:16];
         end
               
         5:begin
             ans = 8'b11011111;
             digit = s[23:20];
         end
       
         6:begin
             ans = 8'b10111111;
             digit =s[27:24];
         end
               
         7:begin
             ans = 8'b01111111;
             digit = s[31:28];
         end
    endcase
    
    seg7 U4(.din(digit),.dout(seg));
endmodule

2022.4/CQU_MIPS/lab1_1/calculate.v
`timescale 1ns / 1ps

// 
module calculate(
    input wire [7:0] num1,
    input wire [2:0] op,
    output [31:0] result
    );
    wire [31:0] num2;
    wire [31:0] Sign_extend;
    
    assign num2 = 32'h00000001;
    assign Sign_extend={{24{1'b0}},num1[7:0]};
    assign result = (op == 3'b000)? Sign_extend + num2:
                    (op == 3'b001)? Sign_extend - num2:
                    (op == 3'b010)? Sign_extend & num2:
                    (op == 3'b011)? Sign_extend | num2:
                    (op == 3'b100)? ~Sign_extend: 32'h00000000;
endmodule

2022.4/CQU_MIPS/lab2/top.v
`timescale 1ns / 1ps
//////////////////////////////////////////////////////////////////////////////////
// Company: 
// Engineer: 
// 
// Create Date: 2015/09/25 10:35:04
// Design Name: 
// Module Name: top
// Project Name: 
// Target Devices: 
// Tool Versions: 
// Description: 
// 
// Dependencies: 
// 
// Revision:
// Revision 0.01 - File Created
// Additional Comments:
// 
//////////////////////////////////////////////////////////////////////////////////


module top(
    input clk,
    input rst,
    input [2:0] op,
    input [7:0] num1,
    output [7:0] ans,
    output [6:0] seg
    );
    wire [31:0] s;
    calculate U1(.num1(num1),.op(op),.result(s));
    
    display U2(.clk(clk),.reset(rst),.s(s),.ans(ans),.seg(seg));
endmodule

2022.4/CQU_MIPS/lab1_1/tb.v
`timescale 1ps/1ps
module tb;

reg clk;
reg rst;
reg [2:0] op;
reg [7:0] num1;
wire [7:0] ans;
wire [6:0] seg;

top test(.clk(clk) , .ans(ans) , .num1(num1) ,
			.op(op) , .seg(seg) , .rst(rst) );
initial begin
	$dumpfile("wave.vcd");
	$dumpvars;
	$monitor("simutime = %g , ans = %d" ,  $time , ans);
end

initial begin
	clk = 0; rst = 1;
	num1[7:0] = 8'h02; op[2:0] = 3'b001;
	#1 rst = 0;
	#100 ; 
	$finish;
end

always begin
	#5 clk = ~clk;
end

endmodule

2022.4/CQU_MIPS/lab1_1/wave.vcd
$date
	Thu Apr 21 07:54:08 2022
$end
$version
	Icarus Verilog
$end
$timescale
	1ps
$end
$scope module tb $end
$var wire 7 ! seg [6:0] $end
$var wire 8 " ans [7:0] $end
$var reg 1 # clk $end
$var reg 8 $ num1 [7:0] $end
$var reg 3 % op [2:0] $end
$var reg 1 & rst $end
$scope module test $end
$var wire 1 # clk $end
$var wire 8 ' num1 [7:0] $end
$var wire 3 ( op [2:0] $end
$var wire 1 & rst $end
$var wire 7 ) seg [6:0] $end
$var wire 32 * s [31:0] $end
$var wire 8 + ans [7:0] $end
$scope module U1 $end
$var wire 8 , num1 [7:0] $end
$var wire 32 - num2 [31:0] $end
$var wire 3 . op [2:0] $end
$var wire 32 / result [31:0] $end
$var wire 32 0 Sign_extend [31:0] $end
$upscope $end
$scope module U2 $end
$var wire 1 # clk $end
$var wire 1 & reset $end
$var wire 32 1 s [31:0] $end
$var wire 7 2 seg [6:0] $end
$var reg 8 3 ans [7:0] $end
$var reg 21 4 count [20:0] $end
$var reg 5 5 digit [4:0] $end
$scope module U4 $end
$var wire 4 6 din [3:0] $end
$var reg 7 7 dout [6:0] $end
$upscope $end
$upscope $end
$upscope $end
$upscope $end
$enddefinitions $end
#0
$dumpvars
bx 7
bx 6
bx 5
b0 4
bx 3
bx 2
b1 1
b10 0
b1 /
b1 .
b1 -
b10 ,
bx +
b1 *
bx )
b1 (
b10 '
1&
b1 %
b10 $
0#
bx "
bx !
$end
#1
0&
#5
b1001111 !
b1001111 )
b1001111 2
b1001111 7
b1 6
b1 5
b11111110 "
b11111110 +
b11111110 3
b1 4
1#
#10
0#
#15
b10 4
1#
#20
0#
#25
b11 4
1#
#30
0#
#35
b100 4
1#
#40
0#
#45
b101 4
1#
#50
0#
#55
b110 4
1#
#60
0#
#65
b111 4
1#
#70
0#
#75
b1000 4
1#
#80
0#
#85
b1001 4
1#
#90
0#
#95
b1010 4
1#
